{"nodes": [{"id": "configo_frontend_src_routes_tsx", "label": "routes.tsx", "file_type": "code", "source_file": "Configo-Frontend/src/routes.tsx", "source_location": "L1"}], "edges": [{"source": "configo_frontend_src_routes_tsx", "target": "react", "relation": "imports_from", "confidence": "EXTRACTED", "source_file": "Configo-Frontend/src/routes.tsx", "source_location": "L48", "weight": 1.0}, {"source": "configo_frontend_src_routes_tsx", "target": "react_router_dom", "relation": "imports_from", "confidence": "EXTRACTED", "source_file": "Configo-Frontend/src/routes.tsx", "source_location": "L49", "weight": 1.0}, {"source": "configo_frontend_src_routes_tsx", "target": "appshellskeleton", "relation": "imports_from", "confidence": "EXTRACTED", "source_file": "Configo-Frontend/src/routes.tsx", "source_location": "L51", "weight": 1.0}, {"source": "configo_frontend_src_routes_tsx", "target": "protectedroutewrapper", "relation": "imports_from", "confidence": "EXTRACTED", "source_file": "Configo-Frontend/src/routes.tsx", "source_location": "L52", "weight": 1.0}, {"source": "configo_frontend_src_routes_tsx", "target": "roleroutewrapper", "relation": "imports_from", "confidence": "EXTRACTED", "source_file": "Configo-Frontend/src/routes.tsx", "source_location": "L53", "weight": 1.0}, {"source": "configo_frontend_src_routes_tsx", "target": "organizationguardwrapper", "relation": "imports_from", "confidence": "EXTRACTED", "source_file": "Configo-Frontend/src/routes.tsx", "source_location": "L54", "weight": 1.0}]}