{"nodes": [{"id": "configo_frontend_tailwind_config_ts", "label": "tailwind.config.ts", "file_type": "code", "source_file": "Configo-Frontend/tailwind.config.ts", "source_location": "L1"}], "edges": [{"source": "configo_frontend_tailwind_config_ts", "target": "tailwindcss", "relation": "imports_from", "confidence": "EXTRACTED", "source_file": "Configo-Frontend/tailwind.config.ts", "source_location": "L1", "weight": 1.0}, {"source": "configo_frontend_tailwind_config_ts", "target": "tailwindcss_animate", "relation": "imports_from", "confidence": "EXTRACTED", "source_file": "Configo-Frontend/tailwind.config.ts", "source_location": "L2", "weight": 1.0}]}